orbit_cli/__main__.py
orbit_cli/cli_application.py
orbit_cli/cli_common.py
orbit_cli/cli_main.py
orbit_cli/cli_utils.py
orbit_cli/templates/application/.gitignore
orbit_cli/templates/application/.version
orbit_cli/templates/application/Makefile
orbit_cli/templates/application/README.md
orbit_cli/templates/application/apt/DEBIAN/control
orbit_cli/templates/application/apt/DEBIAN/postinst
orbit_cli/templates/application/apt/etc/systemd/system/project.service
orbit_cli/templates/application/apt/opt/service/scripts/make_keys.sh
orbit_cli/templates/application/client/App.vue
orbit_cli/templates/application/client/Makefile
orbit_cli/templates/application/client/index.html
orbit_cli/templates/application/client/main.css
orbit_cli/templates/application/client/main.js
orbit_cli/templates/application/client/package.json
orbit_cli/templates/application/client/vite.config.js
orbit_cli/templates/application/common/favicon.ico
orbit_cli/templates/application/common/fonts.txt
orbit_cli/templates/application/common/orbit-logo.png
orbit_cli/templates/application/scripts/VERSION
orbit_cli/templates/application/scripts/roll_version.py
orbit_cli/templates/application/server/Makefile
orbit_cli/templates/application/server/README.md
orbit_cli/templates/application/server/__main__.py
orbit_cli/templates/application/server/make_keys.sh
orbit_cli/templates/application/server/orbit.spec
orbit_cli/templates/application/server/pyproject.toml
orbit_cli/templates/application/server/version.py
orbit_cli/templates/component/.gitignore
orbit_cli/templates/component/.version
orbit_cli/templates/component/Makefile
orbit_cli/templates/component/README.md
orbit_cli/templates/component/client/Makefile
orbit_cli/templates/component/client/index.js
orbit_cli/templates/component/client/main.vue
orbit_cli/templates/component/client/main_old.vue
orbit_cli/templates/component/client/menu.js
orbit_cli/templates/component/client/mytableStore.js
orbit_cli/templates/component/client/package.json
orbit_cli-0.1.26.dist-info/LICENSE.md
orbit_cli-0.1.26.dist-info/METADATA
orbit_cli-0.1.26.dist-info/WHEEL
orbit_cli-0.1.26.dist-info/entry_points.txt
orbit_cli-0.1.26.dist-info/RECORD
